{
	"configurations" : 
	[
		{
			"directories" : 
			[
				{
					"build" : ".",
					"hasInstallRule" : true,
					"jsonFile" : "directory-.-fbff01c335004fb3e52c.json",
					"minimumCMakeVersion" : 
					{
						"string" : "3.12"
					},
					"projectIndex" : 0,
					"source" : ".",
					"targetIndexes" : 
					[
						0,
						1,
						2
					]
				}
			],
			"name" : "",
			"projects" : 
			[
				{
					"directoryIndexes" : 
					[
						0
					],
					"name" : "example_mode_fw_attitude_cpp",
					"targetIndexes" : 
					[
						0,
						1,
						2
					]
				}
			],
			"targets" : 
			[
				{
					"directoryIndex" : 0,
					"id" : "example_mode_fw_attitude::@6890427a1f51a3e7e1df",
					"jsonFile" : "target-example_mode_fw_attitude-a4a86f93d595cc36d1b5.json",
					"name" : "example_mode_fw_attitude",
					"projectIndex" : 0
				},
				{
					"directoryIndex" : 0,
					"id" : "example_mode_fw_attitude_cpp_uninstall::@6890427a1f51a3e7e1df",
					"jsonFile" : "target-example_mode_fw_attitude_cpp_uninstall-236b499f9f5e356a42a8.json",
					"name" : "example_mode_fw_attitude_cpp_uninstall",
					"projectIndex" : 0
				},
				{
					"directoryIndex" : 0,
					"id" : "uninstall::@6890427a1f51a3e7e1df",
					"jsonFile" : "target-uninstall-24a56c3f374ea1fc84d7.json",
					"name" : "uninstall",
					"projectIndex" : 0
				}
			]
		}
	],
	"kind" : "codemodel",
	"paths" : 
	{
		"build" : "/home/janhavi/SwarmRobotics/src/build/example_mode_fw_attitude_cpp",
		"source" : "/home/janhavi/SwarmRobotics/src/px4-ros2-interface-lib/examples/cpp/modes/fw_attitude"
	},
	"version" : 
	{
		"major" : 2,
		"minor" : 3
	}
}
